Ramon/__init__.py
Ramon/loglogreg.py
forecastlib/__init__.py
forecastlib/evaluation/__init__.py
forecastlib/evaluation/evaluation.py
forecastlib/genetics/__init__.py
forecastlib/genetics/coca.py
forecastlib/genetics/pyga.py
forecastlib/libs/BlobLoader.py
forecastlib/libs/MLServiceLoader.py
forecastlib/libs/MappingHelper.py
forecastlib/libs/ModelSerializer.py
forecastlib/libs/__init__.py
forecastlib/models/ClassificationMLModel.py
forecastlib/models/ClassificationModel.py
forecastlib/models/ClassificationNNModel.py
forecastlib/models/ForecastClassificator.py
forecastlib/models/ForecastClassificator3Ranges.py
forecastlib/models/ForecastClassificatorSingle.py
forecastlib/models/ForecastClusterClassificator.py
forecastlib/models/ForecastFlow.py
forecastlib/models/ForecastModel.py
forecastlib/models/ForecastWrapper.py
forecastlib/models/ModelDefinition.py
forecastlib/models/SingleModelClassificator.py
forecastlib/models/__init__.py
forecastlib/training/AbsoluteRelativeError.py
forecastlib/training/ClassificationTrainer.py
forecastlib/training/ForecastTrainer.py
forecastlib/training/Metrics.py
forecastlib/training/ModelAccuracy.py
forecastlib/training/TrainingRunner.py
forecastlib/training/__init__.py
services/ForecastService.py
services/MappingService.py
services/__init__.py
forecastlib-0.2.7.dist-info/METADATA
forecastlib-0.2.7.dist-info/WHEEL
forecastlib-0.2.7.dist-info/top_level.txt
forecastlib-0.2.7.dist-info/RECORD
