Metadata-Version: 2.1
Name: forecastlib
Version: 0.2.7
Summary: Support class for forecasting ML
Home-page: UNKNOWN
Author: Ondrej Pajgrt
Author-email: pajgrt.ondrej@gmail.com
License: UNKNOWN
Platform: UNKNOWN
Classifier: Programming Language :: Python :: 3
Classifier: License :: OSI Approved :: MIT License
Classifier: Operating System :: OS Independent
